<?xml version="1.0" encoding="UTF-8"?>
<quran>
<parabic>ٱ ﻟﺮﱠﺣْﻤَـٰﻦُ</parabic>
<parabic>ﻋَﻠﱠﻢَ ٱ ﻟْﻘُﺮْﺁ نَ</parabic>
<parabic>ﺧَﻠَﻖَ ٱﻹِﻧﺴَﺎ نَ</parabic>
<parabic>ﻋَﻠﱠﻤَﻪُ ٱ ﻟﺒَﻴَﺎ نَ</parabic>
<parabic>ٱ ﻟﺸﱠﻤْﺲُ ﻭَٱ ﻟْﻘَﻤَﺮُ ﺑِﺤُﺴْﺒَﺎ نٍ</parabic>
<parabic>ﻭَٱ ﻟﻨﱠﺠْﻢُ ﻭَٱ ﻟﺸﱠﺠَﺮُ ﻳَﺴْﺠُﺪَﺍ نِ</parabic>
<parabic>ﻭَٱ ﻟﺴﱠﻤَﺂءَ ﺭَﻓَﻌَﻬَﺎ ﻭَﻭَﺿَﻊَ ٱ ﻟْﻤِﻴﺰَﺍ نَ</parabic>
<parabic>أَﻻﱠ ﺗَﻄْﻐَﻮْاْ ﻓِﻰ ٱ ﻟْﻤِﻴﺰَﺍ نِ</parabic>
<parabic>ﻭَأَﻗِﻴﻤُﻮاْ ٱ ﻟْﻮَﺯْ نَ ﺑِﭑ ﻟْﻘِﺴْﻂِ ﻭَﻻَ ﺗُﺨْﺴِﺮُﻭاْ ٱ ﻟْﻤِﻴﺰَﺍ نَ</parabic>
<parabic>ﻭَٱﻷَﺭْضَ ﻭَﺿَﻌَﻬَﺎ  ﻟِﻸَﻧَﺎمِ</parabic>
<parabic>ﻓِﻴﻬَﺎ ﻓَﺎﻛِﻬَﺔٌ ﻭَٱ ﻟﻨﱠﺨْﻞُ ﺫَﺍتُ ٱﻷَﻛْﻤَﺎمِ</parabic>
<parabic>ﻭَٱ ﻟْﺤَﺐﱡ ﺫُو ٱ ﻟْﻌَﺼْﻒِ ﻭَٱ ﻟﺮﱠﻳْﺤَﺎ نُ</parabic>
<parabic>ﻓَﺒِﺄَىﱢ ﺁﻻۤءِ ﺭَﺑﱢﻜُﻤَﺎ ﺗُﻜَﺬﱢﺑَﺎ نِ</parabic>
<parabic>ﺧَﻠَﻖَ ٱﻹِﻧﺴَﺎ نَ ﻣِﻦ ﺻَﻠْﺼَﺎلٍ ﻛَﭑ ﻟْﻔَﺨﱠﺎرِ</parabic>
<parabic>ﻭَﺧَﻠَﻖَ ٱ ﻟْﺠَﺂ نﱠ ﻣِﻦ ﻣﱠﺎﺭِجٍ ﻣﱢﻦ ﻧﱠﺎرٍ</parabic>
<parabic>ﻓَﺒِﺄَىﱢ ﺁﻻۤءِ ﺭَﺑﱢﻜُﻤَﺎ ﺗُﻜَﺬﱢﺑَﺎ نِ</parabic>
<parabic>ﺭَبﱡ ٱ ﻟْﻤَﺸْﺮِﻗَﻴْﻦِ ﻭَﺭَبﱡ ٱ ﻟْﻤَﻐْﺮِﺑَﻴْﻦِ</parabic>
<parabic>ﻓَﺒِﺄَىﱢ ﺁﻻۤءِ ﺭَﺑﱢﻜُﻤَﺎ ﺗُﻜَﺬﱢﺑَﺎ نِ</parabic>
<parabic>ﻣَﺮَجَ ٱ ﻟْﺒَﺤْﺮَﻳْﻦِ ﻳَﻠْﺘَﻘِﻴَﺎ نِ</parabic>
<parabic>ﺑَﻴْﻨَﻬُﻤَﺎ ﺑَﺮْﺯَخٌ ﻻﱠ ﻳَﺒْﻐِﻴَﺎ نِ</parabic>
<parabic>ﻓَﺒِﺄَىﱢ ﺁﻻۤءِ ﺭَﺑﱢﻜُﻤَﺎ ﺗُﻜَﺬﱢﺑَﺎ نِ</parabic>
<parabic>ﻳَﺨْﺮُجُ ﻣِﻨْﻬُﻤَﺎ ﺍ ﻟﱡﻠﺆْ ﻟُﺆُ ﻭَﺍ ﻟﻤَﺮْﺟَﺎ نُ</parabic>
<parabic>ﻓَﺒِﺄَىﱢ ﺁﻻۤءِ ﺭَﺑﱢﻜُﻤَﺎ ﺗُﻜَﺬﱢﺑَﺎ نِ</parabic>
<parabic>ﻭَ ﻟَﻪُ ٱ ﻟْﺠَﻮَﺍرِ ٱ ﻟْﻤُﻨﺸَﺌَﺎتُ ﻓِﻰ ٱ ﻟْﺒَﺤْﺮِ ﻛَﭑﻷَﻋْﻼَمِ</parabic>
<parabic>ﻓَﺒِﺄَىﱢ ﺁﻻۤءِ ﺭَﺑﱢﻜُﻤَﺎ ﺗُﻜَﺬﱢﺑَﺎ نِ</parabic>
<parabic>ﻛُﻞﱡ ﻣَﻦْ ﻋَﻠَﻴْﻬَﺎ ﻓَﺎ نٍ</parabic>
<parabic>ﻭَﻳَﺒْﻘَﻰٰ ﻭَﺟْﻪُ ﺭَﺑﱢﻚَ ﺫُو ٱ ﻟْﺠَﻼَلِ ﻭَٱﻹِﻛْﺮَﺍمِ</parabic>
<parabic>ﻓَﺒِﺄَىﱢ ﺁﻻۤءِ ﺭَﺑﱢﻜُﻤَﺎ ﺗُﻜَﺬﱢﺑَﺎ نِ</parabic>
<parabic>ﻳَﺴْﺄَ ﻟُﻪُ ﻣَﻦ ﻓِﻰ ٱ ﻟﺴﱠﻤَﺎﻭَﺍتِ ﻭَٱﻷَﺭْضِ ﻛُﻞﱠ ﻳَﻮْمٍ ﮧُﻮَ ﻓِﻰ ﺷَﺄْ نٍ</parabic>
<parabic>ﻓَﺒِﺄَىﱢ ﺁﻻۤءِ ﺭَﺑﱢﻜُﻤَﺎ ﺗُﻜَﺬﱢﺑَﺎ نِ</parabic>
<parabic>ﺳَﻨَﻔْﺮُغُ  ﻟَﻜُﻢْ أَﻳﱡﻬَﺎ ٱ ﻟﺜﱠﻘَﻼَ نِ</parabic>
<parabic>ﻓَﺒِﺄَىﱢ ﺁﻻۤءِ ﺭَﺑﱢﻜُﻤَﺎ ﺗُﻜَﺬﱢﺑَﺎ نِ</parabic>
<parabic>ﻳٰﻤَﻌْﺸَﺮَ ٱ ﻟْﺠِﻦﱢ ﻭَٱﻹِﻧﺲِ ﺇِ نِ ٱﺳْﺘَﻄَﻌْﺘُﻢْ أَ ن ﺗَﻨﻔُﺬُﻭاْ ﻣِﻦْ أَﻗْﻄَﺎرِ ٱ ﻟﺴﱠﻤَﺎﻭَﺍتِ ﻭَٱﻷَﺭْضِ ﻓَﭑﻧﻔُﺬُﻭاْ ﻻَ ﺗَﻨﻔُﺬُﻭ نَ ﺇِﻻﱠ ﺑِﺴُﻠْﻄَﺎ نٍ</parabic>
<parabic>ﻓَﺒِﺄَىﱢ ﺁﻻۤءِ ﺭَﺑﱢﻜُﻤَﺎ ﺗُﻜَﺬﱢﺑَﺎ نِ</parabic>
<parabic>ﻳُﺮْﺳَﻞُ ﻋَﻠَﻴْﻜُﻤَﺎ ﺷُﻮَﺍظٌ ﻣﱢﻦ ﻧﱠﺎرٍ ﻭَﻧُﺤَﺎسٌ ﻓَﻼَ ﺗَﻨﺘَﺼِﺮَﺍ نِ</parabic>
<parabic>ﻓَﺒِﺄَىﱢ ﺁﻻۤءِ ﺭَﺑﱢﻜُﻤَﺎ ﺗُﻜَﺬﱢﺑَﺎ نِ</parabic>
<parabic>ﻓَﺈِﺫَا ٱﻧﺸَﻘﱠﺖِ ٱ ﻟﺴﱠﻤَﺂءُ ﻓَﻜَﺎﻧَﺖْ ﻭَﺭْﺩَةً ﻛَﭑ ﻟﺪﱢﮧَﺎ نِ</parabic>
<parabic>ﻓَﺒِﺄَىﱢ ﺁﻻۤءِ ﺭَﺑﱢﻜُﻤَﺎ ﺗُﻜَﺬﱢﺑَﺎ نِ</parabic>
<parabic>ﻓَﻴَﻮْﻣَﺌِﺬٍ ﻻﱠ ﻳُﺴْﺄَلُ ﻋَﻦ ﺫَﻧﺒِﻪِ ﺇِﻧﺲٌ ﻭَﻻَ ﺟَﺂ نٌّ</parabic>
<parabic>ﻓَﺒِﺄَىﱢ ﺁﻻۤءِ ﺭَﺑﱢﻜُﻤَﺎ ﺗُﻜَﺬﱢﺑَﺎ نِ</parabic>
<parabic>ﻳُﻌْﺮَفُ ٱ ﻟْﻤُﺠْﺮِﻣُﻮ نَ ﺑِﺴِﻴﻤَﺎﮧُﻢْ ﻓَﻴُﺆْﺧَﺬُ ﺑِﭑ ﻟﻨﱠﻮَﺍﺻِﻰ ﻭَٱﻷَﻗْﺪَﺍمِ</parabic>
<parabic>ﻓَﺒِﺄَىﱢ ﺁﻻۤءِ ﺭَﺑﱢﻜُﻤَﺎ ﺗُﻜَﺬﱢﺑَﺎ نِ</parabic>
<parabic>ﮧَـٰﺬِﻩِ ﺟَﻬَﻨﱠﻢُ ٱ ﻟﱠﺘِﻰ ﻳُﻜَﺬﱢبُ ﺑِﻬَﺎ ٱ ﻟْﻤُﺠْﺮِﻣُﻮ نَ</parabic>
<parabic>ﻳَﻄُﻮﻓُﻮ نَ ﺑَﻴْﻨَﻬَﺎ ﻭَﺑَﻴْﻦَ ﺣَﻤِﻴﻢٍ ﺁ نٍ</parabic>
<parabic>ﻓَﺒِﺄَىﱢ ﺁﻻۤءِ ﺭَﺑﱢﻜُﻤَﺎ ﺗُﻜَﺬﱢﺑَﺎ نِ</parabic>
<parabic>ﻭَ ﻟِﻤَﻦْ ﺧَﺎفَ ﻣَﻘَﺎمَ ﺭَﺑﱢﻪِ ﺟَﻨﱠﺘَﺎ نِ</parabic>
<parabic>ﻓَﺒِﺄَىﱢ ﺁﻻۤءِ ﺭَﺑﱢﻜُﻤَﺎ ﺗُﻜَﺬﱢﺑَﺎ نِ</parabic>
<parabic>ﺫَﻭَﺍﺗَﺂ أَﻓْﻨَﺎ نٍ</parabic>
<parabic>ﻓَﺒِﺄَىﱢ ﺁﻻۤءِ ﺭَﺑﱢﻜُﻤَﺎ ﺗُﻜَﺬﱢﺑَﺎ نِ</parabic>
<parabic>ﻓِﻴﻬِﻤَﺎ ﻋَﻴْﻨَﺎ نِ ﺗَﺠْﺮِﻳَﺎ نِ</parabic>
<parabic>ﻓَﺒِﺄَىﱢ ﺁﻻۤءِ ﺭَﺑﱢﻜُﻤَﺎ ﺗُﻜَﺬﱢﺑَﺎ نِ</parabic>
<parabic>ﻓِﻴﻬِﻤَﺎ ﻣِﻦ ﻛُﻞﱢ ﻓَﺎﻛِﻬَﺔٍ ﺯَﻭْﺟَﺎ نِ</parabic>
<parabic>ﻓَﺒِﺄَىﱢ ﺁﻻۤءِ ﺭَﺑﱢﻜُﻤَﺎ ﺗُﻜَﺬﱢﺑَﺎ نِ</parabic>
<parabic>ﻣُﺘﱠﻜِﺌِﻴﻦَ ﻋَﻠَﻰ ﻓُﺮُشٍ ﺑَﻄَﺂﺋِﻨُﻬَﺎ ﻣِﻦْ ﺇِﺳْﺘَﺒْﺮَقٍ ﻭَﺟَﻨَﻰ ٱ ﻟْﺠَﻨﱠﺘَﻴْﻦِ ﺩَﺍ نٍ</parabic>
<parabic>ﻓَﺒِﺄَىﱢ ﺁﻻۤءِ ﺭَﺑﱢﻜُﻤَﺎ ﺗُﻜَﺬﱢﺑَﺎ نِ</parabic>
<parabic>ﻓِﻴﻬِﻦﱠ ﻗَﺎﺻِﺮَﺍتُ ٱ ﻟﻄﱠﺮْفِ  ﻟَﻢْ ﻳَﻄْﻤِﺜْﻬُﻦﱠ ﺇِﻧﺲٌ ﻗَﺒْﻠَﻬُﻢْ ﻭَﻻَ ﺟَﺂ نٌّ</parabic>
<parabic>ﻓَﺒِﺄَىﱢ ﺁﻻۤءِ ﺭَﺑﱢﻜُﻤَﺎ ﺗُﻜَﺬﱢﺑَﺎ نِ</parabic>
<parabic>ﻛَﺄَﻧﱠﻬُﻦﱠ ٱ ﻟْﻴَﺎﻗُﻮتُ ﻭَٱ ﻟْﻤَﺮْﺟَﺎ نُ</parabic>
<parabic>ﻓَﺒِﺄَىﱢ ﺁﻻۤءِ ﺭَﺑﱢﻜُﻤَﺎ ﺗُﻜَﺬﱢﺑَﺎ نِ</parabic>
<parabic>ﮧَﻞْ ﺟَﺰَﺁءُ ٱﻹِﺣْﺴَﺎ نِ ﺇِﻻﱠ ٱﻹِﺣْﺴَﺎ نُ</parabic>
<parabic>ﻓَﺒِﺄَىﱢ ﺁﻻۤءِ ﺭَﺑﱢﻜُﻤَﺎ ﺗُﻜَﺬﱢﺑَﺎ نِ</parabic>
<parabic>ﻭَﻣِﻦ ﺩُﻭﻧِﻬِﻤَﺎ ﺟَﻨﱠﺘَﺎ نِ</parabic>
<parabic>ﻓَﺒِﺄَىﱢ ﺁﻻۤءِ ﺭَﺑﱢﻜُﻤَﺎ ﺗُﻜَﺬﱢﺑَﺎ نِ</parabic>
<parabic>ﻣُﺪْﮧَﺂﻣﱠﺘَﺎ نِ</parabic>
<parabic>ﻓَﺒِﺄَىﱢ ﺁﻻۤءِ ﺭَﺑﱢﻜُﻤَﺎ ﺗُﻜَﺬﱢﺑَﺎ نِ</parabic>
<parabic>ﻓِﻴﻬِﻤَﺎ ﻋَﻴْﻨَﺎ نِ ﻧَﻀﱠﺎﺧَﺘَﺎ نِ</parabic>
<parabic>ﻓَﺒِﺄَىﱢ ﺁﻻۤءِ ﺭَﺑﱢﻜُﻤَﺎ ﺗُﻜَﺬﱢﺑَﺎ نِ</parabic>
<parabic>ﻓِﻴﻬِﻤَﺎ ﻓَﺎﻛِﻬَﺔٌ ﻭَﻧَﺨْﻞٌ ﻭَﺭُﻣﱠﺎ نٌ</parabic>
<parabic>ﻓَﺒِﺄَىﱢ ﺁﻻۤءِ ﺭَﺑﱢﻜُﻤَﺎ ﺗُﻜَﺬﱢﺑَﺎ نِ</parabic>
<parabic>ﻓِﻴﻬِﻦﱠ ﺧَﻴْﺮَﺍتٌ ﺣِﺴَﺎ نٌ</parabic>
<parabic>ﻓَﺒِﺄَىﱢ ﺁﻻۤءِ ﺭَﺑﱢﻜُﻤَﺎ ﺗُﻜَﺬﱢﺑَﺎ نِ</parabic>
<parabic>ﺣُﻮرٌ ﻣﱠﻘْﺼُﻮﺭَﺍتٌ ﻓِﻰ ٱ ﻟْﺨِﻴَﺎمِ</parabic>
<parabic>ﻓَﺒِﺄَىﱢ ﺁﻻۤءِ ﺭَﺑﱢﻜُﻤَﺎ ﺗُﻜَﺬﱢﺑَﺎ نِ</parabic>
<parabic> ﻟَﻢْ ﻳَﻄْﻤِﺜْﻬُﻦﱠ ﺇِﻧﺲٌ ﻗَﺒْﻠَﻬُﻢْ ﻭَﻻَ ﺟَﺂ نٌّ</parabic>
<parabic>ﻓَﺒِﺄَىﱢ ﺁﻻۤءِ ﺭَﺑﱢﻜُﻤَﺎ ﺗُﻜَﺬﱢﺑَﺎ نِ</parabic>
<parabic>ﻣُﺘﱠﻜِﺌِﻴﻦَ ﻋَﻠَﻰٰ ﺭَﻓْﺮَفٍ ﺧُﻀْﺮٍ ﻭَﻋَﺒْﻘَﺮِيﱟ ﺣِﺴَﺎ نٍ</parabic>
<parabic>ﻓَﺒِﺄَىﱢ ﺁﻻۤءِ ﺭَﺑﱢﻜُﻤَﺎ ﺗُﻜَﺬﱢﺑَﺎ نِ</parabic>
<parabic>ﺗَﺒَﺎﺭَكَ ٱﺳْﻢُ ﺭَﺑﱢﻚَ ﺫِى ٱ ﻟْﺠَﻼَلِ ﻭَٱﻹِﻛْﺮَﺍمِ</parabic>

<pbangla>Avi[and]ivn[Ú]gv-by| </pbangla>
<pbangla>ÔAvjøvgvj[and] Ky[Ú]iAv-b| </pbangla>
<pbangla>LvjvK[Ú]vj[and] BsQv-b|</pbangla>
<pbangla>ÔAvjøvgvûj[and] evqv-b|</pbangla>
<pbangla>Avk[and]kvgQyIqvjK[Ú]vgviæ weny[Ú]Q[and]ev-b| </pbangla>
<pbangla>IqvbœvRgyIqvk[and]kvRviæ BqvQ[and]R~`v-b| </pbangla>
<pbangla>IqvQ[and] Qvgv[~]Av ivdvÔAvnv-Iqv Iqv`[Ú]vÔAvj[and] gxSv-b| </pbangla>
<pbangla>Avjøv-ZvZ[Ú]vMvI wdj[and] gxSv-b| </pbangla>
<pbangla>Iqv AvK[Ú] xgyj[and] IqvSbv wej[and]wK[Ú]Q[and]wZ[Ú]Iqvjv-ZzL[and]wQiæj[and] gxSv-b| </pbangla>
<pbangla>Iqvj[and] Avi`[Ú]v Iqv `[Ú]vÔAvnv-wjj[and]Avbv-g| </pbangla>
<pbangla>dxnv-dv-wKnvZzIu Iqvb[and]bvL[and]jyh[Ú]v-Zzj[and] AvK[and]gv-g|</pbangla>
<pbangla>Iqvj[and] n[Ú]veŸyhy[Ú]j[and]ÔAvmwd Iqvi[and]ivBn[Ú]v-b|</pbangla>
<pbangla>dvweAvBwq Av-jv[~]B ivweŸKzgv-ZzKvh[and][Ú]wh[Ú]ev-b| </pbangla>
<pbangla>LvjvK[Ú]vj BsQv-bv wgs mvjmv-wjs Kvj[and] dvL[and]Lv-i| </pbangla>
<pbangla>Iqv LvjvK[Ú]vj[and] Rv[~]bœv wg¤§v-wiwRgwgbœv-i[and]| </pbangla>
<pbangla>dvweAvBwq Av-jv[~]B ivweŸKzgv- ZzKvh[and][Ú]wh[Ú]ev-b | </pbangla>
<pbangla>iveŸyj gvk[and]wiK[Ú]vBwb Iqv iveŸyj[and] gvMwievBb| </pbangla>
<pbangla>dvweAvBwq Av-jv[~]B ivweŸKzgv- ZzKvh[and][Ú]wh[Ú]ev-b | </pbangla>
<pbangla>gvivRvj evn[Ú]ivBwb BqvjZvwK[Ú]qv-b| </pbangla>
<pbangla>evBbvûgv-evi[and]SvLyj[and] jv-BqvewMqv-b| </pbangla>
<pbangla>dvweAvBwq Av-jv[~]B ivweŸKzgv- ZzKvh[and][Ú]wh[Ú]ev-b | </pbangla>
<pbangla>BqvLiæR~wgb[and]ûgvj[and] jyÕj~D Iqvj[and] gvi[and] Rv-b| </pbangla>
<pbangla>dvweAvBwq Av-jv[~]B ivweŸKzgv- ZzKvh[and][Ú]wh[Ú]ev-b | </pbangla>
<pbangla>Iqvjvûj[and] RvIqv-wij gyskvAv-Zzwdj evn[Ú]wi Kvj[and]AvÔjv-g| </pbangla>
<pbangla>dvweAvBwq Av-jv[~]B ivweŸKzgv- ZzKvh[and][Ú]wh[Ú]ev-b | </pbangla>
<pbangla>Kzjøygvb[and] ÔAvjvBnv-dv-wbIu| </pbangla>
<pbangla>Iqv Bqve[and][and]K[Ú]v-IqvRû ivweŸKv h[Ú]yj[and] Rvjv-wj Iqvj[and] BK[and]iv-g| </pbangla>
<pbangla>dvweAvBwq Av-jv[~]B ivweŸKzgv- ZzKvh[and][Ú]wh[Ú]ev-b | </pbangla>
<pbangla>BqvQ[and]Avjyn~gvs wdQ[and] Qvgv-Iqv-wZ Iqvj[and] Aviw`[Ú] Kzjøv BqvIwgb[and] ûIqv dx kvÕb[and]|</pbangla>
<pbangla>dvweAvBwq Av-jv[~]B ivweŸKzgv- ZzKvh[and][Ú]wh[Ú]ev-b|</pbangla>
<pbangla>Qvbvdiæ¸ jvKzg[and] AvBqynvQ[Ü]Q[Ü]vK[Ú]vjv-b| </pbangla>
<pbangla>dvweAvBwq Av-jv[~]B ivweŸKzgv- ZzKvh[and][Ú]wh[Ú]ev-b | </pbangla>
<pbangla>Bqv-gvÔkvivj wRwbœ Iqvj[and] BswQ BwbQZvZ[Ú]vÔZzg Avs Zvsdzh~[Ú]wgb[and] AvK[Ú]Z[Ú]v-wiQ[and] QvgvIqv-wZ Iqvj[and] Aviw`[Ú]dvsdzh~[Ú] jv-Zvsdzh[Ú]~bv Bjøv-weQyjZ[Ú]v-b[and]|</pbangla>
<pbangla>dvweAvBwq Av-jv[~]B ivweŸKzgv- ZzKvh[and][Ú]wh[Ú]ev-b | </pbangla>
<pbangla>BDiQvjyÔAvjvBKzgv-ïIqv-Ry [Ü]g[and] wgb[and]bv-wiIu Iqv byn[Ú]v-Qys dvjv-ZvsZvwmiv-b|</pbangla>
<pbangla>dvweAvBwq Av-jv[~]B ivweŸKzgv- ZzKvh[and][Ú]wh[Ú]ev-b | </pbangla>
<pbangla>dvBh[Ú]vs kvK[Ú]K[Ú]vwZQ[and] Qvgv[~]D dvKv-bvZ[and] Iqvi`vZvs KvwÏnv-b| </pbangla>
<pbangla>dvweAvBwq Av-jv[~]B ivweŸKzgv- ZzKvh[and][Ú]wh[Ú]ev-b | </pbangla>
<pbangla>dvBqvIgv Bwh[Ú]jøv-BDQ[and]AvjyÔAvs h[Ú]vg[and]wenx[˜] BsQyIu Iqvjv-Rv[~]b|</pbangla>
<pbangla>dvweAvBwq Av-jv[~]B ivweŸKzgv- ZzKvh[and][Ú]wh[Ú]ev-b | </pbangla>
<pbangla>BDÔivdzj[and] gyRwig~bv weQxgv-ûg[and] dvBDÕLvh[Ú]ywebœvIqv-Qx Iqvj AvK[Ú]`v-g| </pbangla>
<pbangla>dvweAvBwq Av-jv[~]B ivweŸKzgv- ZzKvh[and][Ú]wh[Ú]ev-b | </pbangla>
<pbangla>nv-wh[Ú]nx RvnvbœvgyjøvZx BDKvh[Ú][and]wh [Ú]eywenvj[and] gyRwig~b| </pbangla>
<pbangla>BqvZ~ [Ú]d‚bv evBbvnv-Iqv evBbv n[Ú]vgxwgb[and] Av-b| </pbangla>
<pbangla>dvweAvBwq Av-jv[~]B ivweŸKzgv- ZzKvh[and][Ú]wh[Ú]ev-b | </pbangla>
<pbangla>Iqv wjgvb[and] Lv-dv gvK[Ú]v-gv ivweŸnx RvbœvZv-b| </pbangla>
<pbangla>dvweAvBwq Av-jv[~]B ivweŸKzgv- ZzKvh[and][Ú]wh[Ú]ev-b | </pbangla>
<pbangla>h[Ú]vIqv-Zv[˜] Avd[and]bv-b[and]| </pbangla>
<pbangla>dvweAvBwq Av-jv[~]B ivweŸKzgv- ZzKvh[and][Ú]wh[Ú]ev-b |</pbangla>
<pbangla>dxwngv-ÔAvBbv-wb ZvRwiqv-b| </pbangla>
<pbangla>dvweAvBwq Av-jv[~]B ivweŸKzgv- ZzKvh[and][Ú]wh[Ú]ev-b | </pbangla>
<pbangla>dxwngv-wgs Kzwjø dv-wKnvwZs SvIRv-b| </pbangla>
<pbangla>dvweAvBwq Av-jv[~]B ivweŸKzgv- ZzKvh[and][Ú]wh[Ú]ev-b |</pbangla>
<pbangla>gyËvwKCbv ÔAvjv-dziæwkg[and] evZ[Ú]v[~]Bbynv-wgb[and] BQ[and]Zve[and]ivwK[Ú]I Iqv Rvbvj RvbœvZvBwb `v-b[and]|</pbangla>
<pbangla>dvweAvBwq Av-jv[~]B ivweŸKzgv- ZzKvh[and][Ú]wh[Ú]ev-b | </pbangla>
<pbangla>dxwnbœv K[Ú]v-wmiv-ZzË[Ú]vi[and]wd jvg[and] BqvZ[Ú]wgQ[and][Ü]ûbœv BsQys K[Ú]ve[and]jvûg[and] Iqvjv-Rv[~]b|</pbangla>
<pbangla>dvweAvBwq Av-jv[~]B ivweŸKzgv- ZzKvh[and][Ú]wh[Ú]ev-b | </pbangla>
<pbangla>KvAvbœvûbœvj[and] BqvÔK~[Ú]ZzIqvj gviRvb-b| </pbangla>
<pbangla>dvweAvBwq Av-jv[~]B ivweŸKzgv- ZzKvh[and][Ú]wh[Ú]ev-b | </pbangla>
<pbangla>nvj[and] RvSv[~]Dj[and] Bn[Ú]Qv-wb Bjøvj[and] Bn[Ú]Qv-b| </pbangla>
<pbangla>dvweAvBwq Av-jv[~]B ivweŸKzgv- ZzKvh[and][Ú]wh[Ú]ev-b | </pbangla>
<pbangla>Iqv wgs `~wbwngv-RvbœvZv-b| </pbangla>
<pbangla>dvweAvBwq Av-jv[~]B ivweŸKzgv- ZzKvh[and][Ú]wh[Ú]ev-b | </pbangla>
<pbangla>gy`[and] n~g[and]gvZv-b| </pbangla>
<pbangla>dvweAvBwq Av-jv[~]B ivweŸKzgv- ZzKvh[and][Ú]wh[Ú]ev-b | </pbangla>
<pbangla>dxwngv-ÔAvBbv-wb bvÏ[Ú]vLvZv-b| </pbangla>
<pbangla>dvweAvBwq Av-jv[~]B ivweŸKzgv- ZzKvh[and][Ú]wh[Ú]ev-b | </pbangla>
<pbangla>dxwngv-dv-wKnvZzIu Iqv bvL[and]jyIu Iqviæ¤§v-b| </pbangla>
<pbangla>dvweAvBwq Av-jv[~]B ivweŸKzgv- ZzKvh[and][Ú]wh[Ú]ev-b | </pbangla>
<pbangla>dxwnbœv LvBiv-Zzb wn[Ú]Qv-b| </pbangla>
<pbangla>dvweAvBwq Av-jv[~]B ivweŸKzgv- ZzKvh[and][Ú]wh[Ú]ev-b | </pbangla>
<pbangla>n~[Ú]iæg[and]gvK[Ú]m~iv-Zzs wdj[and] wLqv-g| </pbangla>
<pbangla>dvweAvBwq Av-jv[~]B ivweŸKzgv- ZzKvh[and][Ú]wh[Ú]ev-b | </pbangla>
<pbangla>jvg[and] BqvZ[Ú]wgQ[and][Ü]ûbœv BsQys K[Ú]ve[and]jvûg[and] Iqvjv-Rv[~]b[and]| </pbangla>
<pbangla>dvweAvBwq Av-jv[~]B ivweŸKzgv- ZzKvh[and][Ú]wh[Ú]ev-b | </pbangla>
<pbangla>gyËvwKCbv ÔAvjv-ivd[and]ivwdb[and] Ly`[Ú]wiIu Iqv ÔAve[and]K[Ú]vwiBwqb[and] wn[Ú]Qv-b[and]| </pbangla>
<pbangla>dvweAvBwq Av-jv[~]B ivweŸKzgv- ZzKvh[and][Ú]wh[Ú]ev-b | </pbangla>
<pbangla>Zvev-ivKvQ[and]gyivweŸKv wh[Ú]j[and] Rvjv-wj Iqvj[and] BK[and]iv-g| </pbangla>

<tbangla>Ki“bvgq Avj­vn|</tbangla>
<tbangla>wk¶v w`‡q‡Qb ‡KviAvb,</tbangla>
<tbangla>m…wó K‡i‡Qb gvbyl,</tbangla>
<tbangla>Zv‡K wkwL‡q‡Qb eY©bv|</tbangla>
<tbangla>m~h© I P›`ª wnmvegZ P‡j|</tbangla>
<tbangla>Ges Z…YjZv I e…¶vw` ‡mR`viZ Av‡Q|</tbangla>
<tbangla>wZwb AvKvk‡K K‡i‡Qb mgybœZ Ges ¯’vcb K‡i‡Qb Zyjv`Û|</tbangla>
<tbangla>hv‡Z ‡Zvgiv mxgvjsNb bv Ki Zyjv`‡Û|</tbangla>
<tbangla>‡Zvgiv b¨vh¨ IRb Kv‡qg Ki Ges IR‡b Kg w`‡qv bv|</tbangla>
<tbangla>wZwb c…w_ex‡K ¯’vcb K‡i‡Qb m…óRx‡ei R‡b¨|</tbangla>
<tbangla>G‡Z Av‡Q djg~j Ges ewniveiYwewkó LR©yi e…¶|</tbangla>
<tbangla>Avi Av‡Q ‡Lvmvwewkó km¨ I myMwÜ dyj|</tbangla>
<tbangla>AZGe, ‡Zvgiv Df‡q ‡Zvgv‡`i cvjbKZ©vi ‡Kvb ‡Kvb AbyMªn‡K A¯^xKvi Ki‡e?</tbangla>
<tbangla>wZwb gvbyl‡K m…wó K‡i‡Qb ‡cvov gvwUi b¨vq ï®‹ g…wËKv ‡_‡K|</tbangla>
<tbangla>Ges wRb‡K m…wó K‡i‡Qb AwMœwkLv ‡_‡K|</tbangla>
<tbangla>AZGe, ‡Zvgiv Df‡q ‡Zvgv‡`i cvjbKZ©vi ‡Kvb ‡Kvb AbyMªn A¯^xKvi Ki‡e?</tbangla>
<tbangla>wZwb `yB D`qvPj I `yB A¯—vP‡ji gvwjK|</tbangla>
<tbangla>AZGe, ‡Zvgiv Df‡q ‡Zvgv‡`i cvjbKZ©vi ‡Kvb ‡Kvb Ae`vb‡K A¯^xKvi Ki‡e?</tbangla>
<tbangla>wZwb cvkvcvwk `yB `wiqv cªevwnZ K‡i‡Qb|</tbangla>
<tbangla>Df‡qi gvSLv‡b i‡q‡Q GK Aš—ivj, hv Zviv AwZµg K‡i bv|</tbangla>
<tbangla>AZGe, ‡Zvgiv Df‡q ‡Zvgv‡`i cvjbKZ©vi ‡Kvb ‡Kvb Ae`vb‡K A¯^xKvi Ki‡e?</tbangla>
<tbangla>Dfq `wiqv ‡_‡K Drcbœ nq ‡gvwZ I cªevj|</tbangla>
<tbangla>AZGe, ‡Zvgiv Df‡q ‡Zvgv‡`i cvjbKZ©vi ‡Kvb ‡Kvb Ae`vb‡K A¯^xKvi Ki‡e?</tbangla>
<tbangla>`wiqvq wePiYkxj ce©Z`…k¨ RvnvRmg~n ZvuiB (wbqš¿bvaxb)</tbangla>
<tbangla>AZGe, ‡Zvgiv Df‡q ‡Zvgv‡`i cvjbKZ©vi ‡Kvb ‡Kvb Ae`vb‡K A¯^xKvi Ki‡e?</tbangla>
<tbangla>f~c…‡ói mewKQyB aŸsmkxj|</tbangla>
<tbangla>GKgvÎ Avcbvi gwngvq I gnvbyfe cvjbKZ©vi mËv Qvov|</tbangla>
<tbangla>AZGe, ‡Zvgiv Df‡q ‡Zvgv‡`i cvjbKZ©vi ‡Kvb ‡Kvb Ae`vb‡K A¯^xKvi Ki‡e?</tbangla>
<tbangla>b‡fvgÛj I f~gÛ‡ji mevB Zvui Kv‡Q cªv_©x| wZwb me©`vB ‡Kvb bv ‡Kvb Kv‡R iZ Av‡Qb|</tbangla>
<tbangla>AZGe, ‡Zvgiv Df‡q ‡Zvgv‡`i cvjbKZ©vi ‡Kvb ‡Kvb Ae`vb‡K A¯^xKvi Ki‡e?</tbangla>
<tbangla>‡n wRb I gvbe! Avwg kxNªB ‡Zvgv‡`i R‡b¨ Kg©gy³ n‡q hve|</tbangla>
<tbangla>AZGe, ‡Zvgiv Df‡q ‡Zvgv‡`i cvjbKZ©vi ‡Kvb ‡Kvb Ae`vb‡K A¯^xKvi Ki‡e?</tbangla>
<tbangla>‡n wRb I gvbeK~j, b‡fvgÛj I f~gÛ‡ji cªvš— AwZµg Kiv hw` ‡Zvgv‡`i mv‡a¨ Kyjvq, Z‡e AwZµg Ki| wKš‘ QvocÎ e¨ZxZ ‡Zvgiv Zv AwZµg Ki‡Z cvi‡e bv|</tbangla>
<tbangla>AZGe, ‡Zvgiv Df‡q ‡Zvgv‡`i cvjbKZ©vi ‡Kvb ‡Kvb Ae`vb‡K A¯^xKvi Ki‡e?</tbangla>
<tbangla>Qvov n‡e ‡Zvgv‡`i cªwZ AwMœùywj½ I aygªKyÄ ZLb ‡Zvgiv ‡mme cªwZnZ Ki‡Z cvi‡e bv|</tbangla>
<tbangla>AZGe, ‡Zvgiv Df‡q ‡Zvgv‡`i cvjbKZ©vi ‡Kvb ‡Kvb Ae`vb‡K A¯^xKvi Ki‡e?</tbangla>
<tbangla>‡hw`b AvKvk we`xY© n‡e ZLb ‡mwU i³e‡Y© iwÄZ Pvgovi gZ n‡q hv‡e|</tbangla>
<tbangla>AZGe, ‡Zvgiv Df‡q ‡Zvgv‡`i cvjbKZ©vi ‡Kvb ‡Kvb Ae`vb‡K A¯^xKvi Ki‡e?</tbangla>
<tbangla>‡mw`b gvbyl bv Zvi Aciva m¤ú‡K© wRÁvwmZ n‡e, bv wRb|</tbangla>
<tbangla>AZGe, ‡Zvgiv Df‡q ‡Zvgv‡`i cvjbKZ©vi ‡Kvb ‡Kvb Ae`vb‡K A¯^xKvi Ki‡e?</tbangla>
<tbangla>Acivax‡`i cwiPq cvIqv hv‡e Zv‡`i ‡Pnviv ‡_‡K; AZtci Zv‡`i Kcv‡ji Pyj I cv a‡i ‡U‡b ‡bqv n‡e|</tbangla>
<tbangla>AZGe, ‡Zvgiv Df‡q ‡Zvgv‡`i cvjbKZ©vi ‡Kvb ‡Kvb Ae`vb‡K A¯^xKvi Ki‡e?</tbangla>
<tbangla>GUvB Rvnvbœvg, hv‡K Acivaxiv wg_¨v ejZ|</tbangla>
<tbangla>Zviv Rvnvbœv‡gi AwMœ I dyUš— cvwbi gvSLv‡b cª`w¶Y Ki‡e|</tbangla>
<tbangla>AZGe, ‡Zvgiv Df‡q ‡Zvgv‡`i cvjbKZ©vi ‡Kvb ‡Kvb Ae`vb‡K A¯^xKvi Ki‡e?</tbangla>
<tbangla>‡h e¨w³ Zvi cvjbKZ©vi mvg‡b ‡ck nIqvi fq iv‡L, Zvi R‡b¨ i‡q‡Q `yÕwU D`¨vb|</tbangla>
<tbangla>AZGe, ‡Zvgiv Df‡q ‡Zvgv‡`i cvjbKZ©vi ‡Kvb ‡Kvb Ae`vb‡K A¯^xKvi Ki‡e?</tbangla>
<tbangla>Dfq D`¨vbB Nb kvLv-cj­ewewkó|</tbangla>
<tbangla>AZGe, ‡Zvgiv Df‡q ‡Zvgv‡`i cvjbKZ©vi ‡Kvb ‡Kvb Ae`vb‡K A¯^xKvi Ki‡e?</tbangla>
<tbangla>Dfq D`¨v‡b Av‡Q engvb `yB cªmªeb|</tbangla>
<tbangla>AZGe, ‡Zvgiv Df‡q ‡Zvgv‡`i cvjbKZ©vi ‡Kvb ‡Kvb Ae`vb‡K A¯^xKvi Ki‡e?</tbangla>
<tbangla>Df‡qi g‡a¨ cª‡Z¨K dj wewfbœ iK‡gi n‡e|</tbangla>
<tbangla>AZGe, ‡Zvgiv Df‡q ‡Zvgv‡`i cvjbKZ©vi ‡Kvb ‡Kvb Ae`vb‡K A¯^xKvi Ki‡e?</tbangla>
<tbangla>Zviv Z_vq ‡ik‡gi Av¯—iwewkó weQvbvq ‡njvb w`‡q em‡e| Dfq D`¨v‡bi dj Zv‡`i wbKU Syj‡e|</tbangla>
<tbangla>AZGe, ‡Zvgiv Df‡q ‡Zvgv‡`i cvjbKZ©vi ‡Kvb ‡Kvb Ae`vb‡K A¯^xKvi Ki‡e?</tbangla>
<tbangla>Z_vq _vK‡e AvbZbqb igbxMb, ‡Kvb wRb I gvbe c~‡e© hv‡`i e¨envi K‡iwb|</tbangla>
<tbangla>AZGe, ‡Zvgiv Df‡q ‡Zvgv‡`i cvjbKZ©vi ‡Kvb ‡Kvb Ae`vb‡K A¯^xKvi Ki‡e?</tbangla>
<tbangla>cªevj I cÙivM m`…k igYxMY|</tbangla>
<tbangla>AZGe, ‡Zvgiv Df‡q ‡Zvgv‡`i cvjbKZ©vi ‡Kvb ‡Kvb Ae`vb‡K A¯^xKvi Ki‡e?</tbangla>
<tbangla>mrKv‡Ri cªwZ`vb DËg cyi¯‹vi e¨ZxZ wK n‡Z cv‡i?</tbangla>
<tbangla>AZGe, ‡Zvgiv Df‡q ‡Zvgv‡`i cvjbKZ©vi ‡Kvb ‡Kvb Ae`vb‡K A¯^xKvi Ki‡e?</tbangla>
<tbangla>GB `yÕwU Qvov AviI `yÕwU D`¨vb i‡q‡Q|</tbangla>
<tbangla>AZGe, ‡Zvgiv Df‡q ‡Zvgv‡`i cvjbKZ©vi ‡Kvb ‡Kvb Ae`vb‡K A¯^xKvi Ki‡e?</tbangla>
<tbangla>Kv‡jvgZ Nb meyR|</tbangla>
<tbangla>AZGe, ‡Zvgiv Df‡q ‡Zvgv‡`i cvjbKZ©vi ‡Kvb ‡Kvb Ae`vb‡K A¯^xKvi Ki‡e?</tbangla>
<tbangla>Z_vq Av‡Q D‡ØwjZ `yB cªmªeY|</tbangla>
<tbangla>AZGe, ‡Zvgiv Df‡q ‡Zvgv‡`i cvjbKZ©vi ‡Kvb ‡Kvb Ae`vb‡K A¯^xKvi Ki‡e?</tbangla>
<tbangla>Z_vq Av‡Q dj-g~j, LR©yi I Avbvi|</tbangla>
<tbangla>AZGe, ‡Zvgiv Df‡q ‡Zvgv‡`i cvjbKZ©vi ‡Kvb ‡Kvb Ae`vb‡K A¯^xKvi Ki‡e?</tbangla>
<tbangla>‡mLv‡b _vK‡e m”PwiÎv my›`ix igYxMY|</tbangla>
<tbangla>AZGe, ‡Zvgiv Df‡q ‡Zvgv‡`i cvjbKZ©vi ‡Kvb ‡Kvb Ae`vb‡K A¯^xKvi Ki‡e?</tbangla>
<tbangla>Zvuey‡Z Ae¯’vbKvwiYx ûiMY|</tbangla>
<tbangla>AZGe, ‡Zvgiv Df‡q ‡Zvgv‡`i cvjbKZ©vi ‡Kvb ‡Kvb Ae`vb‡K A¯^xKvi Ki‡e?</tbangla>
<tbangla>‡Kvb wRb I gvbe c~‡e© Zv‡`i‡K ¯úk© K‡iwb|</tbangla>
<tbangla>AZGe, ‡Zvgiv Df‡q ‡Zvgv‡`i cvjbKZ©vi ‡Kvb ‡Kvb Ae`vb‡K A¯^xKvi Ki‡e?</tbangla>
<tbangla>Zviv meyR gmb‡` Ges DrK…ó g~j¨evb weQvbvq ‡njvb w`‡q em‡e|</tbangla>
<tbangla>AZGe, ‡Zvgiv Df‡q ‡Zvgv‡`i cvjbKZ©vi ‡Kvb ‡Kvb Ae`vb‡K A¯^xKvi Ki‡e?</tbangla>
<tbangla>KZ c~Y¨gq Avcbvi cvjbKZ©vi bvg, whwb gwngvgq I gnvbyfe|</tbangla>

</quran>